pyomnix/__init__.py
pyomnix/consts.py
pyomnix/omnix_logger.py
pyomnix/data_process/__init__.py
pyomnix/data_process/data_manipulator.py
pyomnix/data_process/financial.py
pyomnix/model_interface/__init__.py
pyomnix/model_interface/agents.py
pyomnix/model_interface/model_flow.py
pyomnix/model_interface/models.py
pyomnix/pltconfig/__init__.py
pyomnix/pltconfig/color_preset.py
pyomnix/pltconfig/matplotlib_config_tex_pgf.py
pyomnix/pltconfig/plot_config_notex.py
pyomnix/pltconfig/plot_config_tex.py
pyomnix/pltconfig/plot_config_tex_pgf.py
pyomnix/utils/__init__.py
pyomnix/utils/data.py
pyomnix/utils/env.py
pyomnix/utils/math.py
pyomnix/utils/plot.py
pyomnix-0.1b1.dist-info/licenses/LICENSE
pyomnix-0.1b1.dist-info/METADATA
pyomnix-0.1b1.dist-info/WHEEL
pyomnix-0.1b1.dist-info/entry_points.txt
pyomnix-0.1b1.dist-info/top_level.txt
pyomnix-0.1b1.dist-info/RECORD
