Metadata-Version: 2.4
Name: pyomnix
Version: 0.1b1
Summary: Integrated Tools for Scientific Computing, Data Analysis, and AI Development
Author-email: Dongkai <dongkai001@e.ntu.edu.sg>
License-Expression: MIT
Project-URL: Homepage, https://github.com/panasee/PyOmnix
Project-URL: Repository, https://github.com/panasee/PyOmnix.git
Keywords: data-analysis,scientific-computing,ai,machine-learning,visualization,workflow
Classifier: Development Status :: 3 - Alpha
Classifier: Programming Language :: Python
Classifier: Intended Audience :: Science/Research
Classifier: Intended Audience :: Developers
Classifier: Topic :: Scientific/Engineering
Classifier: Topic :: Scientific/Engineering :: Information Analysis
Classifier: Topic :: Scientific/Engineering :: Visualization
Classifier: Topic :: Software Development :: Libraries :: Python Modules
Requires-Python: >=3.11
License-File: LICENSE
Requires-Dist: pillow
Requires-Dist: numpy
Requires-Dist: pandas
Requires-Dist: matplotlib
Requires-Dist: waitress
Requires-Dist: plotly>=5.24.0
Requires-Dist: kaleido==0.1.0.post1
Requires-Dist: jupyter
Requires-Dist: dash
Requires-Dist: prefect>=3.2.9
Requires-Dist: langchain>=0.3.20
Requires-Dist: langgraph>=0.3.18
Requires-Dist: langchain-deepseek
Requires-Dist: langchain-huggingface
Requires-Dist: langchain-openai
Requires-Dist: langchain-anthropic
Requires-Dist: langchain-google-genai
Requires-Dist: langchain-community
Requires-Dist: pydantic>=2.10.6
Provides-Extra: gui
Requires-Dist: PyQt6>=6.7.0; extra == "gui"
Provides-Extra: dev
Requires-Dist: ruff>=0.10.0; extra == "dev"
Requires-Dist: mypy>=1.15.0; extra == "dev"
Requires-Dist: black>=25.1.0; extra == "dev"
Requires-Dist: isort>=6.0.1; extra == "dev"
Requires-Dist: pre-commit>=4.2.0; extra == "dev"
Dynamic: license-file
